JqmobiDoc/README.md
JqmobiDoc/__init__.py
JqmobiDoc/__main__.py
JqmobiDoc/file.epub
JqmobiDoc/index.html
JqmobiDoc/css/__init__.py
JqmobiDoc/css/annotations.css
JqmobiDoc/css/main.css
JqmobiDoc/css/normalize.css
JqmobiDoc/css/popup.css
JqmobiDoc/font/__init__.py
JqmobiDoc/font/fontello.eot
JqmobiDoc/font/fontello.svg
JqmobiDoc/font/fontello.ttf
JqmobiDoc/font/fontello.woff
JqmobiDoc/img/__init__.py
JqmobiDoc/img/annotator-glyph-sprite.png
JqmobiDoc/img/annotator-icon-sprite.png
JqmobiDoc/img/apple-touch-icon.png
JqmobiDoc/img/cancelfullscreen.png
JqmobiDoc/img/close.png
JqmobiDoc/img/fullscreen.png
JqmobiDoc/img/loader.gif
JqmobiDoc/img/menu-icon.png
JqmobiDoc/img/save.png
JqmobiDoc/img/saved.png
JqmobiDoc/img/settings-s.png
JqmobiDoc/img/settings.png
JqmobiDoc/img/star.png
JqmobiDoc/js/__init__.py
JqmobiDoc/js/epub.js
JqmobiDoc/js/epub.min.js
JqmobiDoc/js/epub.min.map
JqmobiDoc/js/hooks.min.js
JqmobiDoc/js/hooks.min.map
JqmobiDoc/js/reader.js
JqmobiDoc/js/reader.js.map
JqmobiDoc/js/reader.min.js
JqmobiDoc/js/reader.min.map
JqmobiDoc/js/hooks/__init__.py
JqmobiDoc/js/hooks/extensions/__init__.py
JqmobiDoc/js/hooks/extensions/highlight.js
JqmobiDoc/js/libs/__init__.py
JqmobiDoc/js/libs/jquery.min.js
JqmobiDoc/js/libs/localforage.min.js
JqmobiDoc/js/libs/screenfull.js
JqmobiDoc/js/libs/screenfull.min.js
JqmobiDoc/js/libs/zip.min.js
JqmobiDoc/js/plugins/__init__.py
JqmobiDoc/js/plugins/hypothesis.js
JqmobiDoc/js/plugins/search.js
jqmobi_doc-2024.3.2.0.dist-info/METADATA
jqmobi_doc-2024.3.2.0.dist-info/WHEEL
jqmobi_doc-2024.3.2.0.dist-info/entry_points.txt
jqmobi_doc-2024.3.2.0.dist-info/top_level.txt
jqmobi_doc-2024.3.2.0.dist-info/RECORD
